metaforward.py
metaforward-0.1a1.dist-info/LICENSE.md
metaforward-0.1a1.dist-info/METADATA
metaforward-0.1a1.dist-info/WHEEL
metaforward-0.1a1.dist-info/top_level.txt
metaforward-0.1a1.dist-info/RECORD
